[{"name": "", "audio": "", "normalized": ["the taimanin's home base was located"]}, {"name": "", "audio": "", "normalized": ["somewhere in the hidden city, gosha."]}, {"name": "", "audio": "", "normalized": ["to the taimanin, their most cherished facility was the gosha academy, where future taimanin train day and night."]}, {"name": "", "audio": "", "normalized": ["naturally, it wasn't easy to enter on account of the near-impregnable defenses propped up by the special taimanin forces."]}, {"name": "", "audio": "", "normalized": ["however, by using the powers stolen from an elite demon, the man was able to infiltrate the gosha academy under the disguise of a teacher called tanaka."]}, {"name": "", "audio": "", "normalized": ["the power he had obtained worked like a prison, able to trap anyone's heart within it."]}, {"name": "", "audio": "", "normalized": ["using the power meant he could manipulate a person's thoughts, reasoning, and even memories."]}, {"name": "", "audio": "", "normalized": ["he could make them do the strangest things all without them ever realizing it."]}, {"name": "", "audio": "", "normalized": ["'even if a person was released from this \"prison"]}, {"name": "", "audio": "", "normalized": ["of course, the man had his sights on the most powerful taimanin, asagi igawa."]}, {"name": "", "audio": "", "normalized": ["preparations were already set for his big move."]}, {"name": "", "audio": "", "normalized": ["after class, the man headed to the principal's office where he knew asagi was waiting."]}, {"name": "", "audio": "", "normalized": ["he'd spent all this time getting ready.", " today was finally the day he could train her."]}, {"name": "Sakura", "audio": "v_sr063_sakura_0000", "normalized": ["oh, tanaka-chan!"]}, {"name": "", "audio": "", "normalized": ["sakura, asagi's younger sister came bursting into the hall, stopping suddenly when she saw the man."]}, {"name": "You", "audio": "", "normalized": ["sakura-sensei, is everything alright?"]}, {"name": "Sakura", "audio": "v_sr063_sakura_0001", "normalized": ["are you off to see my sister?"]}, {"name": "You", "audio": "", "normalized": ["huh?", " oh yes, i have business with the principal today."]}, {"name": "", "audio": "", "normalized": ["sakura rolled her eyes greatly upon hearing the man's answer."]}, {"name": "Sakura", "audio": "v_sr063_sakura_0002", "normalized": ["wait a minute!", " you aren't dating my older sister, are you?"]}, {"name": "", "audio": "", "normalized": ["she asked, with other students walking by in the hall.", " for a teacher, she sure was oblivious to her surroundings."]}, {"name": "You", "audio": "", "normalized": ["just what do you think is going on?"]}, {"name": "Sakura", "audio": "v_sr063_sakura_0003", "normalized": ["well you see… i've noticed you guys see each other a lot, but when i asked if you were dating she would say…"]}, {"name": "Sakura", "audio": "v_sr063_sakura_0004", "normalized": ["…that she never sees you or she would lie and just not tell me anything!"]}, {"name": "", "audio": "", "normalized": ["sakura's voice carried a tinge of disappointment."]}, {"name": "You", "audio": "", "normalized": ["hahaha, well then take her word for it."]}, {"name": "Sakura", "audio": "v_sr063_sakura_0005", "normalized": ["wait, really?"]}, {"name": "You", "audio": "", "normalized": ["it's true i greatly respect principal asagi, but i'm merely studying under her.", " actually, may i ask why you're in such a rush?"]}, {"name": "Sakura", "audio": "v_sr063_sakura_0006", "normalized": ["oh, shoot!", " mucchan is gonna be pissed!"]}, {"name": "", "audio": "", "normalized": ["sakura darted off like a scared rabbit."]}, {"name": "You", "audio": "", "normalized": ["(what's gotten into her all of a sudden…)"]}, {"name": "", "audio": "", "normalized": ["the man knew there was more to sakura than meets the eye.", " sure, she seemed childish and silly,"]}, {"name": "", "audio": "", "normalized": ["but the accomplishments she and murasaki yatsu made throughout the years were no joke."]}, {"name": "", "audio": "", "normalized": ["sakura was the type of character that if underestimated, would come back and bite you in the ass."]}, {"name": "", "audio": "", "normalized": ["perhaps she had already seen asagi for what she really was."]}, {"name": "", "audio": "", "normalized": ["even still, they're sisters.", " she'd be the first to notice if her sister acted differently."]}, {"name": "You", "audio": "", "normalized": ["(is that why she asked a leading question?", ")"]}, {"name": "", "audio": "", "normalized": ["regardless, he shouldn't let his guard down."]}, {"name": "", "audio": "", "normalized": ["it might even be a good idea to take asagi outside of the school, he thought."]}, {"name": "", "audio": "", "normalized": ["the man pondered this as he knocked on the principal's door."]}, {"name": "You", "audio": "", "normalized": ["it's tanaka.", " asagi-sensei, do you have a moment?"]}, {"name": "Asagi", "audio": "v_sr063_0000", "normalized": ["tanaka-sensei?", " please come in."]}, {"name": "You", "audio": "", "normalized": ["thank you for seeing me."]}, {"name": "Asagi", "audio": "v_sr063_0001", "normalized": ["what seems the be the problem, tanaka-sensei?"]}, {"name": "", "audio": "", "normalized": ["asagi was beaming as she welcomed the man."]}, {"name": "", "audio": "", "normalized": ["her eyes sparkled seeing the newly appointed teacher."]}, {"name": "You", "audio": "", "normalized": ["you see, i was thinking of asking you out on a date."]}, {"name": "Asagi", "audio": "v_sr063_0002", "normalized": ["wh-what?!"]}, {"name": "", "audio": "", "normalized": ["normally, tanaka-sensei would have never said something like that."]}, {"name": "", "audio": "", "normalized": ["asagi was clearly shocked, but being an adult meant she could easily hide her true feelings.", " her expression returned, and she asked the man,"]}, {"name": "Asagi", "audio": "v_sr063_0003", "normalized": ["what's gotten into you all of a sudden?", " is this some kind of joke?"]}, {"name": "You", "audio": "", "normalized": ["it's not a joke, asagi-sensei.", " i am genuinely asking you out on a date.", " of course, this will also include sex."]}, {"name": "Asagi", "audio": "v_sr063_0004", "normalized": ["…"]}, {"name": "", "audio": "", "normalized": ["asagi's eyebrows twitched as she furrowed them."]}, {"name": "Asagi", "audio": "v_sr063_0005", "normalized": ["tanaka-sensei, it seems you're not feeling well.", " you should perhaps go home and take some time off."]}, {"name": "", "audio": "", "normalized": ["she was restraining her voice, but one could see the rage building up in her eyes.", " she wanted to kill him."]}, {"name": "You", "audio": "", "normalized": ["there's no need for that.", " 'i am asagi's lover.", "'\""]}, {"name": "Asagi", "audio": "v_sr063_0006", "normalized": ["ah—!"]}, {"name": "", "audio": "", "normalized": ["instantly asagi was knocked off her feet on to the floor."]}, {"name": "You", "audio": "", "normalized": ["are you alright?"]}, {"name": "", "audio": "", "normalized": ["the man said, propping her up."]}, {"name": "Asagi", "audio": "v_sr063_0007", "normalized": ["ah… yeah… i'm fine… i just felt a bit dizzy…"]}, {"name": "", "audio": "", "normalized": ["she said, peering up at him.", " however, her tone was not something one would use towards someone as perverted as the man."]}, {"name": "", "audio": "", "normalized": ["no, she was looking at him lovingly."]}, {"name": "", "audio": "", "normalized": ["the man knew his power had an effect over asagi."]}, {"name": "", "audio": "", "normalized": ["they were now lovers."]}, {"name": "", "audio": "", "normalized": ["they loved each other not just as taimanin but also as fellow teachers."]}, {"name": "", "audio": "", "normalized": ["and that's why he had to train her all over school and the town.", " but to asagi, she viewed this only as a means of building their relationship."]}, {"name": "", "audio": "", "normalized": ["naturally, asagi couldn't remember any of this."]}, {"name": "", "audio": "", "normalized": ["at the snap of his fingers, he could make her forget all the lust and joy she had just experienced."]}, {"name": "", "audio": "", "normalized": ["without her even realizing it, the prison he kept her heart in grew stronger each time he gave her pleasure."]}, {"name": "You", "audio": "", "normalized": ["are you tired?"]}, {"name": "Asagi", "audio": "v_sr063_0008", "normalized": ["a bit yeah… school has been causing me a ton of grief lately…"]}, {"name": "", "audio": "", "normalized": ["asagi showed him a weaker side of herself that she would never show anyone else."]}, {"name": "You", "audio": "", "normalized": ["you're just overworked, asagi.", " let's change things up and go on a date.", " say, what do you think about the beach?"]}, {"name": "", "audio": "", "normalized": ["the man asked, tightly gripping her waist."]}, {"name": "Asagi", "audio": "v_sr063_0009", "normalized": ["bu-but i still have work to do…"]}, {"name": "You", "audio": "", "normalized": ["it's me or the work.", " which is more important?"]}, {"name": "Asagi", "audio": "v_sr063_0010", "normalized": ["…of course, you…"]}, {"name": "", "audio": "", "normalized": ["the skill was working perfectly."]}, {"name": "", "audio": "", "normalized": ["he knew he could make her answer whatever question he wanted, regardless of how mean it was."]}, {"name": "You", "audio": "", "normalized": ["why don't we have some fun at the public beach again?"]}, {"name": "", "audio": "", "normalized": ["he said as he slipped his hand up her skirt and slapped her pussy."]}, {"name": "Asagi", "audio": "v_sr063_0011", "normalized": ["wait, not here.", " recently sakura has been getting suspicious of us…"]}, {"name": "You", "audio": "", "normalized": ["i just talked to her.", " she asked if we were dating."]}, {"name": "Asagi", "audio": "v_sr063_0012", "normalized": ["see?", " we should wait until we get to the beach…"]}, {"name": "", "audio": "", "normalized": ["she said, whispering into his ear.", " she was ready for sex."]}, {"name": "You", "audio": "", "normalized": ["that settles it, then."]}, {"name": "", "audio": "", "normalized": ["asagi and the man left the hidden village by car and headed past the mountains, straight towards the coast by the river."]}, {"name": "", "audio": "", "normalized": ["this area was famous for being a popular tourist attraction."]}, {"name": "", "audio": "", "normalized": ["there's also a seaside school where students from the gosha academy would go to learn swimming at."]}, {"name": "", "audio": "", "normalized": ["it was the busiest time of the year."]}, {"name": "", "audio": "", "normalized": ["asagi and the man arrived at the beach resort where thousands of tourists were enjoying themselves."]}, {"name": "Asagi", "audio": "v_sr063_0013", "normalized": ["i can't believe this is the bikini you chose…"]}, {"name": "You", "audio": "", "normalized": ["looks good on you, asagi."]}, {"name": "Asagi", "audio": "v_sr063_0014", "normalized": ["i'm so embarrassed i could die…"]}, {"name": "", "audio": "", "normalized": ["the way she looked now made her voice tremble more than if she were actually nude."]}, {"name": "You", "audio": "", "normalized": ["don't worry.", " nobody's gonna know it's you, asagi."]}, {"name": "Asagi", "audio": "v_sr063_0015", "normalized": ["that's not it… just look at me!"]}, {"name": "You", "audio": "", "normalized": ["i picked it out for you.", " i thought it would be perfect.", " and i was right."]}, {"name": "Asagi", "audio": "v_sr063_0016", "normalized": ["you're always like this… idiot."]}, {"name": "", "audio": "", "normalized": ["asagi tried to play it off like she was shy or bashful, but one could tell by her soft voice that she was kind of enjoying this."]}, {"name": "", "audio": "", "normalized": ["the warm ocean waves crashed against both of their thighs."]}, {"name": "", "audio": "", "normalized": ["he wore an extremely normal bathing suit while asagi wore a high-leg one-piece.", " to make matters worse, asagi's bathing suit was almost see-through."]}, {"name": "", "audio": "", "normalized": ["anyone could easily see her bright-pink nipples and the deep crevice of her pussy.", " she was bare for everyone to see."]}, {"name": "", "audio": "", "normalized": ["the only thing hiding her identity was a pair of dark sunglasses the man had prepared."]}, {"name": "", "audio": "", "normalized": ["her toned and muscular taimanin body exceeded anything a model could ever dream of.", " within moments, asagi had the attention of all the males there."]}, {"name": "Asagi", "audio": "v_sr063_0017", "normalized": ["everyone's… …looking at me…"]}, {"name": "You", "audio": "", "normalized": ["it's because you're amazing…"]}, {"name": "", "audio": "", "normalized": ["the man whispered as he caressed her body from behind."]}, {"name": "Asagi", "audio": "v_sr063_0018", "normalized": ["aah, no…wait…"]}, {"name": "", "audio": "", "normalized": ["asagi twisted both her legs, unable to close them the moment she entered the beach."]}, {"name": "", "audio": "", "normalized": ["she couldn't close them on account of the giant vibrator the man stuck up there."]}, {"name": "", "audio": "", "normalized": ["the mega-sized vibrator was a great fit for her, but the very end stuck out and gyrated, causing her crotch to look like she had a strange bulge."]}, {"name": "Asagi", "audio": "v_sr063_0019", "normalized": ["hahh…mmnn…"]}, {"name": "", "audio": "", "normalized": ["the crashing waves helped stifle the loud mechanical noise produced by the vibrator.", " asagi couldn't stop herself from moaning."]}, {"name": "You", "audio": "", "normalized": ["do you like it, asagi?"]}, {"name": "Asagi", "audio": "v_sr063_0020", "normalized": ["hah, what do you think?", " hnngh…"]}, {"name": "You", "audio": "", "normalized": ["everyone's looking at you and thinking how perverted you are.", " you're just a crazy bitch enjoying her vibrator.", " it's plain to see."]}, {"name": "Asagi", "audio": "v_sr063_0021", "normalized": ["aah… you're… you're terrible… if…if it weren't for who you are, you'd be dead by now…"]}, {"name": "You", "audio": "", "normalized": ["is that why your nipples are so hard?", " they're about to pop out of your suit."]}, {"name": "Asagi", "audio": "v_sr063_0022", "normalized": ["please… don't draw attention to them…"]}, {"name": "", "audio": "", "normalized": ["asagi became small with embarrassment."]}, {"name": "", "audio": "", "normalized": ["the man didn't even need to point it out.", " her nipples were rock hard, and she was soaked."]}, {"name": "", "audio": "", "normalized": ["the waves helped draw out more of asagi's fluids from her soaked crotch."]}, {"name": "You", "audio": "", "normalized": ["how does it feel to wear such a tiny bikini in front of all these thirsty men?", " i'm sure you feel really sexy, asagi."]}, {"name": "Asagi", "audio": "v_sr063_0023", "normalized": ["why… you're always making me do strange things… why do you…hnnghh…"]}, {"name": "You", "audio": "", "normalized": ["you were always a masochistic pig.", " all i did was give you a stage."]}, {"name": "Asagi", "audio": "v_sr063_0024", "normalized": ["you're so mean…"]}, {"name": "", "audio": "", "normalized": ["her subordinates would never believe such a thing— that her and her boyfriend would do such a thing as this."]}, {"name": "You", "audio": "", "normalized": ["heh, check it out.", " there's some men from goshamachi looking at you."]}, {"name": "Asagi", "audio": "v_sr063_0025", "normalized": ["wh-what?!"]}, {"name": "", "audio": "", "normalized": ["asagi shot straight up."]}, {"name": "Asagi", "audio": "v_sr063_0026", "normalized": ["aahh!"]}, {"name": "", "audio": "", "normalized": ["the vibrator was cranked higher, which caught asagi by surprise and made her scream."]}, {"name": "You", "audio": "", "normalized": ["it's right next door.", " but i'm sure none of them suspect that the highly esteemed principal of the gosha academy"]}, {"name": "You", "audio": "", "normalized": ["and leader of the taimanin would do such a thing."]}, {"name": "Asagi", "audio": "v_sr063_0027", "normalized": ["stop…please…"]}, {"name": "Asagi", "audio": "v_sr063_0028", "normalized": ["if they were found out… that's it… everything will be ruined if they find out…"]}, {"name": "", "audio": "", "normalized": ["she said, as her moans became louder and louder."]}, {"name": "", "audio": "", "normalized": ["perhaps she enjoyed the excitement of being found out."]}, {"name": "You", "audio": "", "normalized": ["alright, let's be careful and not get caught… i'll just turn this down a little—oops!"]}, {"name": "Asagi", "audio": "v_sr063_0029", "normalized": ["n-noo!"]}, {"name": "", "audio": "", "normalized": ["*bzzt!", "*"]}, {"name": "Asagi", "audio": "v_sr063_0030", "normalized": ["hnngghh!"]}, {"name": "", "audio": "", "normalized": ["asagi grit her teeth."]}, {"name": "", "audio": "", "normalized": ["her face grimaced as she did her best trying to withstand the intense sensations of the vibrator."]}, {"name": "", "audio": "", "normalized": ["she tried to hold herself still, but it was useless.", " her body was rocked by the waves as the machine gyrated inside her."]}, {"name": "Asagi", "audio": "v_sr063_0031", "normalized": ["mmnn… the vibrator is…too…strong…"]}, {"name": "You", "audio": "", "normalized": ["it's only at mid-strength, you know."]}, {"name": "Asagi", "audio": "v_sr063_0032", "normalized": ["no way… but… aah… it feels stronger than before… mmnn…"]}, {"name": "You", "audio": "", "normalized": ["that's probably because it's all the way up there.", " it's probably teasing your cervix."]}, {"name": "Asagi", "audio": "v_sr063_0033", "normalized": ["yes…yesyes… that's it…"]}, {"name": "", "audio": "", "normalized": ["she tried to shut her mouth, but soft moans continued to spill out."]}, {"name": "", "audio": "", "normalized": ["from the look of her face, it seemed as if she wanted to say something."]}, {"name": "Asagi", "audio": "v_sr063_0034", "normalized": ["aah…mmn… hnnghh… honey…"]}, {"name": "You", "audio": "", "normalized": ["yes?"]}, {"name": "Asagi", "audio": "v_sr063_0035", "normalized": ["aahh… pl-please… tu-turn down…mmnn…the…strength…"]}, {"name": "", "audio": "", "normalized": ["she pleaded to the man, trying her best to control her voice."]}, {"name": "Asagi", "audio": "v_sr063_0036", "normalized": ["i… i can't help but moan… i can't…hold them…back… it's…too…strong…"]}, {"name": "", "audio": "", "normalized": ["her body tweaked and twinged almost as if she was holding in her bladder.", " she looked like she was going to explode."]}, {"name": "", "audio": "", "normalized": ["with her mouth not being a viable way for her body to express itself, her legs began to twitch as a thick flow of liquid began streaming down her thighs."]}, {"name": "You", "audio": "", "normalized": ["but you're doing so well suppressing them."]}, {"name": "Asagi", "audio": "v_sr063_0037", "normalized": ["please… i won't…be able to… hold on…much longer…"]}, {"name": "Asagi", "audio": "v_sr063_0038", "normalized": ["the vibrator is hitting my cervix… feels so weird… i…oh god…"]}, {"name": "You", "audio": "", "normalized": ["are you at the limit already?"]}, {"name": "Asagi", "audio": "v_sr063_0039", "normalized": ["yes…yes i am… i really am…"]}, {"name": "You", "audio": "", "normalized": ["oh, brother.", " so this is all the mighty taimanin warrior can take?", " i thought you were stronger than this."]}, {"name": "Asagi", "audio": "v_sr063_0040", "normalized": ["it's because i'm in front of you… please understand…"]}, {"name": "", "audio": "", "normalized": ["with tears welling in her eyes, asagi's whole body shook as she pleaded him to stop."]}, {"name": "You", "audio": "", "normalized": ["fiine.", " i'll weaken it a bit."]}, {"name": "", "audio": "", "normalized": ["the man showed her that he was turning the device off but—"]}, {"name": "Asagi", "audio": "v_sr063_0041", "normalized": ["haah…haah… thank you…"]}, {"name": "", "audio": "", "normalized": ["just as she started to calm down, the man turned it right back on."]}, {"name": "", "audio": "", "normalized": ["*bzzt!", "*"]}, {"name": "Asagi", "audio": "v_sr063_0042", "normalized": ["hnngghh!", " aahh!"]}, {"name": "", "audio": "", "normalized": ["her body began violently twitching, as if her crotch had been struck with lightning."]}, {"name": "Asagi", "audio": "v_sr063_0043", "normalized": ["hhnnggh!", " aahhnngghh!"]}, {"name": "", "audio": "", "normalized": ["she rocked her hair back and forth as she bit down hard doing all she could to suppress her moans."]}, {"name": "You", "audio": "", "normalized": ["see?", " i knew you still had some fight in you.", " that's my girl."]}, {"name": "Asagi", "audio": "v_sr063_0044", "normalized": ["hnngghh!", " mmpphh!"]}, {"name": "", "audio": "", "normalized": ["though her mouth was closed, it was clear she wanted to scream at him."]}, {"name": "You", "audio": "", "normalized": ["you're really something, asagi."]}, {"name": "Asagi", "audio": "v_sr063_0045", "normalized": ["hmmpphh?!"]}, {"name": "", "audio": "", "normalized": ["the man stuck his hands down her wet bathing suit from behind."]}, {"name": "", "audio": "", "normalized": ["he could feel her warm body heat up the water trapped behind her bathing suit— her sweaty body ached to be touched."]}, {"name": "Asagi", "audio": "v_sr063_0046", "normalized": ["mmnn… hnnghh…"]}, {"name": "", "audio": "", "normalized": ["she shied away in an attempt to have him stop."]}, {"name": "", "audio": "", "normalized": ["but he did not heed her request.", " instead he fished around inside her suit, finally coming up and cupping her breasts."]}, {"name": "", "audio": "", "normalized": ["using his fingers, he pressed deeply into her tough and hard nipples."]}, {"name": "Asagi", "audio": "v_sr063_0047", "normalized": ["mmnngghh!"]}, {"name": "", "audio": "", "normalized": ["asagi moaned loudly as her body shook with pleasure."]}, {"name": "", "audio": "", "normalized": ["it seems she came a little just from the sensation of having her breasts fondled."]}, {"name": "Asagi", "audio": "v_sr063_0048", "normalized": ["…aah!"]}, {"name": "", "audio": "", "normalized": ["from her tiny slit shot short jets of cum as the vibrator writhed and turned inside her."]}, {"name": "You", "audio": "", "normalized": ["hah, looks like you came, asagi."]}, {"name": "Asagi", "audio": "v_sr063_0049", "normalized": ["hnnghh… honey… no more… if this continues then… i… aah…"]}, {"name": "", "audio": "", "normalized": ["asagi was now talking through the tiny gaps in her teeth."]}, {"name": "You", "audio": "", "normalized": ["what?", " you mean you don't want to cum more?"]}, {"name": "Asagi", "audio": "v_sr063_0050", "normalized": ["no, not that… just… i mean, look where we are… people will begin to notice…"]}, {"name": "You", "audio": "", "normalized": ["yes.", " you're just a shivering weirdo if you only had a vibrator up your pussy…"]}, {"name": "You", "audio": "", "normalized": ["…but people couldn't not notice if i was here fondling your tits under your bathing suit."]}, {"name": "Asagi", "audio": "v_sr063_0051", "normalized": ["that's right… so… hnnghh… just please…stop already…"]}, {"name": "You", "audio": "", "normalized": ["but that's strange, because your tits are begging me to continue."]}, {"name": "", "audio": "", "normalized": ["the man whispered as he jiggled her tits slightly in his hand."]}, {"name": "", "audio": "", "normalized": ["her suit wrapped tightly across his hand which perfectly outlined what he was doing."]}, {"name": "", "audio": "", "normalized": ["the men standing around all knew what was happening."]}, {"name": "Asagi", "audio": "v_sr063_0052", "normalized": ["mmn… aahh… no more… stop massaging them… oohh…"]}, {"name": "", "audio": "", "normalized": ["asagi tried her best to remove herself from the growing stimulation.", " her soft moans became impossible to hold down, and she shook with suppressed titillation."]}, {"name": "Asagi", "audio": "v_sr063_0053", "normalized": ["aah…mmnn…oohh… hnnghh…mnn…"]}, {"name": "", "audio": "", "normalized": ["however, it was plain to see she was a dirty woman who truly loved being massaged by her lover—regardless of where she was."]}, {"name": "", "audio": "", "normalized": ["'voices growing louder than the crashing waves could be heard.", " \"woah, that's fucking hot!", "\" \"check her out!", "\" the men were getting riled up."]}, {"name": "", "audio": "", "normalized": ["'however, women shrieked, \"what a slut!", "\" \"is she fucked in the head, or what?", "\" were they perhaps jealous?"]}, {"name": "You", "audio": "", "normalized": ["asagi, can you hear them?", " they're talking about you."]}, {"name": "Asagi", "audio": "v_sr063_0054", "normalized": ["please… no more… i'm so embarrassed… i think i'm going to lose my mind… oh god…"]}, {"name": "You", "audio": "", "normalized": ["but look!", " you can see that all the man are hard.", " you've singlehandedly made all of them hard, asagi!"]}, {"name": "Asagi", "audio": "v_sr063_0055", "normalized": ["hnngghh!"]}, {"name": "", "audio": "", "normalized": ["she yelled at him, only after stealing a quick glance at their cocks."]}, {"name": "", "audio": "", "normalized": ["she gave out a moan, but one could tell she was inches away from losing control."]}, {"name": "", "audio": "", "normalized": ["wrapped in embarrassment and pleasure, her whole body just would not stop shaking with ecstasy."]}, {"name": "You", "audio": "", "normalized": ["don't you want to show them something even dirtier?"]}, {"name": "Asagi", "audio": "v_sr063_0056", "normalized": ["n…no… please… any more and i'll… i'll do anything… just please…"]}, {"name": "Asagi", "audio": "v_sr063_0057", "normalized": ["i'm going to lose my mind… really, this'll be the…end of me… please, just stop…"]}, {"name": "You", "audio": "", "normalized": ["alright, alright."]}, {"name": "", "audio": "", "normalized": ["the man looked at her like he was about to stop.", " then, in one swift motion."]}, {"name": "You", "audio": "", "normalized": ["psych!"]}, {"name": "Asagi", "audio": "v_sr063_0058", "normalized": ["ahh!"]}, {"name": "", "audio": "", "normalized": ["asagi grit her teeth tightly in anticipation for what was going to happen."]}, {"name": "", "audio": "", "normalized": ["but she would never expect that he would set the vibrator to max while he violently tugged on her tits from left to right."]}, {"name": "Asagi", "audio": "v_sr063_0059", "normalized": ["aahh!"]}, {"name": "", "audio": "", "normalized": ["all of her hard work was done in an instant as she let out unbridled sultry moans."]}, {"name": "", "audio": "", "normalized": ["her tongue jutted from her mouth, and deep bellowing moans echoed out as she melted in his hands."]}, {"name": "Asagi", "audio": "v_sr063_0060", "normalized": ["haah!", " aah-aah!", " aahh"]}, {"name": "", "audio": "", "normalized": ["her legs wobbled and shock as the vibrator rocked her on max settings.", " it looked like it was going to shoot out."]}, {"name": "", "audio": "", "normalized": ["it seemed as if there was little need for her bathing suit as copious amounts of asagi cream seeped through the fabric will little problem."]}, {"name": "Asagi", "audio": "v_sr063_0061", "normalized": ["aah-aah-aah-aah!", " please stop!", " i can't take anymoorree!"]}, {"name": "You", "audio": "", "normalized": ["what's the matter, asagi?", " didn't you say you didn't want to get found out?"]}, {"name": "", "audio": "", "normalized": ["the man said as he kneaded her breasts like he was making dough."]}, {"name": "", "audio": "", "normalized": ["her nipples were so hard they became difficult to invert."]}, {"name": "", "audio": "", "normalized": ["the man slid his fingers across them, though he feared they could bust a hole through his hand—they were that hard."]}, {"name": "Asagi", "audio": "v_sr063_0062", "normalized": ["no moorree!", " i can't take this anymoorree!"]}, {"name": "Asagi", "audio": "v_sr063_0063", "normalized": ["your strong hands massaging my tits while my pussy gets blown out by this vibrator… it's too much!"]}, {"name": "Asagi", "audio": "v_sr063_0064", "normalized": ["there's no way i can withstand all this!"]}, {"name": "", "audio": "", "normalized": ["by now asagi was well aware the men could hear her voice.", " even still, she grinded up against the man as she enjoyed the ride."]}, {"name": "", "audio": "", "normalized": ["with the vibrator still inside her, she pushed her ass against his turgid cock, inviting him to a little fun."]}, {"name": "Asagi", "audio": "v_sr063_0065", "normalized": ["haahh!", " aahh!", " dear… deeaarr!"]}, {"name": "You", "audio": "", "normalized": ["asagi, i want you to cum for these men.", " show them the stupid face you make when you cum!"]}, {"name": "", "audio": "", "normalized": ["the moment he said that, her whole body reacted violently by shaking in place, as if she had touched a live wire."]}, {"name": "Asagi", "audio": "v_sr063_0066", "normalized": ["no!", " please, anything but that!", " there's so many people!", " i can't show my ahegao at the beach!", " please, no!"]}, {"name": "You", "audio": "", "normalized": ["but you really do want to cum, right?", " doesn't looking like this get you hot?", " don't play dumb with me."]}, {"name": "Asagi", "audio": "v_sr063_0067", "normalized": ["stop it!", " no more or else… i… i might just cum!", " i might make cummy cumm-aahh!"]}, {"name": "You", "audio": "", "normalized": ["'i am asagi's lover.", "' do it."]}, {"name": "Asagi", "audio": "v_sr063_0068", "normalized": ["hyaahh!"]}, {"name": "", "audio": "", "normalized": ["asagi shot her head back."]}, {"name": "", "audio": "", "normalized": ["a look of unhindered passion took over her as she looked at the men.", " she was moments away from orgasm."]}, {"name": "Asagi", "audio": "v_sr063_0069", "normalized": ["darling!", " i'm gonna cum!", " your lover is gonna cum!", " everyone, look at me!"]}, {"name": "Asagi", "audio": "v_sr063_0070", "normalized": ["everyone at the beach!", " i'm gonna cum my brains out!", " come look at me!", " over here!"]}, {"name": "", "audio": "", "normalized": ["the men's erect penises propped up in unison the moment asagi moaned in ecstasy."]}, {"name": "Asagi", "audio": "v_sr063_0071", "normalized": ["aahh!", " i'm cuummiinngg!"]}, {"name": "", "audio": "", "normalized": ["asagi gave everyone a show to remember."]}, {"name": "", "audio": "", "normalized": ["from her crotch erupted a stream with enough vigor, one might mistake it for piss."]}, {"name": "Asagi", "audio": "v_sr063_0072", "normalized": ["yeess!", " this feels amaazziinngg!"]}, {"name": "Asagi", "audio": "v_sr063_0073", "normalized": ["everyone's seeing me cuumm!", " i'm such a dirty whoore!"]}, {"name": "", "audio": "", "normalized": ["her legs twitched and shook.", " everyone had a clear view of her beautiful orgasm."]}, {"name": "You", "audio": "", "normalized": ["asagi, you're a true exhibitionist slut!"]}, {"name": "", "audio": "", "normalized": ["just as asagi was melting with orgasm, the man took his finger nails and drove them deep into her nipples, causing her to almost fall over."]}, {"name": "Asagi", "audio": "v_sr063_0074", "normalized": ["that's right!", " that's right!", " that's riight!"]}, {"name": "Asagi", "audio": "v_sr063_0075", "normalized": ["everyone can see me!", " they're all watching me cuumm!"]}, {"name": "Asagi", "audio": "v_sr063_0076", "normalized": ["i'm a dirty exhibitionist whooree!"]}, {"name": "", "audio": "", "normalized": ["her hair shook and became disheveled as she added more liquid to the already expansive ocean."]}, {"name": "You", "audio": "", "normalized": ["hey look.", " there's even kids watching."]}, {"name": "Asagi", "audio": "v_sr063_0077", "normalized": ["ki-kids?!"]}, {"name": "", "audio": "", "normalized": ["asagi winced and trembled."]}, {"name": "Girl", "audio": "", "normalized": ["mama, what's that strange woman doing?"]}, {"name": "Girl's Mother", "audio": "", "normalized": ["huh?", "—no!", " don't look, honey!"]}, {"name": "Asagi", "audio": "v_sr063_0078", "normalized": ["aah…aahh… that kid just saw me… they totally saw me doing this nasty thing… i'm a monster!", " a failure of a human being!"]}, {"name": "", "audio": "", "normalized": ["seeing a mother, let alone her child see her in this state made asagi cringe with disgust.", " she truly felt lower than low."]}, {"name": "Asagi", "audio": "v_sr063_0079", "normalized": ["aah-aah-aahh!", " i'm cumming!", " i'm such a failluurree!", " cummiinngg"]}, {"name": "Asagi", "audio": "v_sr063_0080", "normalized": ["aahh!"]}, {"name": "You", "audio": "", "normalized": ["now let's show everyone your face!"]}, {"name": "", "audio": "", "normalized": ["the man placed his hands on her sunglasses."]}, {"name": "Asagi", "audio": "v_sr063_0081", "normalized": ["eegghh!", " let'sh do iitt!", " aah-aah-aahh!"]}, {"name": "", "audio": "", "normalized": ["the continuously orgasming asagi didn't even try to resist."]}, {"name": "Asagi", "audio": "v_sr063_0082", "normalized": ["aahh…aahh… aahh!"]}, {"name": "", "audio": "", "normalized": ["what a mess.", " asagi's face grimaced in orgasm as the spectators watched on."]}, {"name": "Asagi", "audio": "v_sr063_0083", "normalized": ["haah…aah…haah… haah…mmn…"]}, {"name": "", "audio": "", "normalized": ["eyes rolled back into her head, tongue jutting out—asagi was really a sight."]}, {"name": "Asagi", "audio": "v_sr063_0084", "normalized": ["they're looking at mee… i look so stupiid… but they're looking…"]}, {"name": "", "audio": "", "normalized": ["thick strands of drool spilled from her lips as she spoke."]}, {"name": "You", "audio": "", "normalized": ["don't worry.", " even if someone in the crowd recognizes you, i'll make sure it never gets out.", " you can count on me."]}, {"name": "Asagi", "audio": "v_sr063_0085", "normalized": ["ahh… good… i'm finished if it does… i'll be finished…aahh…finished…"]}, {"name": "", "audio": "", "normalized": ["though she sat there and repeated the words 'i'm finished' over and over again, it seemed as if deep down, she actually wanted that."]}, {"name": "Asagi", "audio": "v_sr063_0086", "normalized": ["it just…felt…so good… the way…you…fool around… it's…amazing…"]}, {"name": "Asagi", "audio": "v_sr063_0087", "normalized": ["you've really…turned me into a… truly…dirty woman…aahh…"]}, {"name": "You", "audio": "", "normalized": ["let's go before they call the cops.", " we'll continue this later."]}, {"name": "Asagi", "audio": "v_sr063_0088", "normalized": ["aah… that sounds great…"]}, {"name": "", "audio": "", "normalized": ["she whispered, exasperated by her continuous climaxing, as she left herself in his hands."]}, {"name": "", "audio": "", "normalized": ["at this point, she had almost gone bow-legged from cumming so many times in a row."]}, {"name": "", "audio": "", "normalized": ["her legs were left quivering as the vibrator remained inside.", " a constant stream of pussy juice streamed down her legs."]}]